lydian/__init__.py
lydian/apps/__init__.py
lydian/apps/base.py
lydian/apps/config.py
lydian/apps/console.py
lydian/apps/interface.py
lydian/apps/iperf.py
lydian/apps/mocktraffic.py
lydian/apps/monitor.py
lydian/apps/namespace.py
lydian/apps/podium.py
lydian/apps/recorder.py
lydian/apps/results.py
lydian/apps/rules.py
lydian/apps/tcpdump.py
lydian/apps/traffic_controller.py
lydian/apps/internal/__init__.py
lydian/apps/internal/hostinfo.py
lydian/apps/internal/setup.py
lydian/apps/pentest/__init__.py
lydian/apps/pentest/lynis.py
lydian/apps/pentest/rapidscan.py
lydian/apps/watch/__init__.py
lydian/apps/watch/threat.py
lydian/common/__init__.py
lydian/common/background.py
lydian/common/consts.py
lydian/common/core.py
lydian/common/db.py
lydian/common/errors.py
lydian/controller/__init__.py
lydian/controller/client.py
lydian/controller/rpyc_controller.py
lydian/data/__init__.py
lydian/data/esx_firewall.xml
lydian/data/lydian.conf
lydian/data/lydian.service
lydian/data/lydian_esx.service
lydian/data/lydian_esx.sh
lydian/recorder/__init__.py
lydian/recorder/es_client.py
lydian/recorder/record.py
lydian/recorder/wf_client.py
lydian/tests/__init__.py
lydian/tests/demo.py
lydian/tests/test_rapidscan.py
lydian/tests/apps/__init__.py
lydian/tests/apps/test_rules.py
lydian/tests/common/__init__.py
lydian/tests/common/test_background.py
lydian/tests/integration/__init__.py
lydian/tests/integration/test_lydian.py
lydian/tests/integration/test_mocktraffic.py
lydian/tests/integration/test_service.py
lydian/tests/traffic/__init__.py
lydian/tests/traffic/test_http_server.py
lydian/tests/traffic/test_manager.py
lydian/traffic/__init__.py
lydian/traffic/client.py
lydian/traffic/connection.py
lydian/traffic/core.py
lydian/traffic/manager.py
lydian/traffic/server.py
lydian/traffic/task.py
lydian/utils/__init__.py
lydian/utils/api_server.py
lydian/utils/common.py
lydian/utils/install.py
lydian/utils/logger.py
lydian/utils/lpsutil.py
lydian/utils/mock.py
lydian/utils/network_utils.py
lydian-1.0.1.dist-info/LICENSE.txt
lydian-1.0.1.dist-info/METADATA
lydian-1.0.1.dist-info/NOTICE.txt
lydian-1.0.1.dist-info/WHEEL
lydian-1.0.1.dist-info/top_level.txt
lydian-1.0.1.dist-info/RECORD
