Metadata-Version: 2.1
Name: lydian
Version: 1.0.1
Summary: A generic Distributed (Python) Applications Platform
Home-page: https://github.com/vmware/distributed-apps-platform
Author: Vipin Sharma, Pradeep Singh, Spiro Kourtessis, Gavin Chang, Mahima Kothari, Kaustabh Duorah
Author-email: sharmavipin@vmware.com
License: UNKNOWN
Platform: UNKNOWN
Classifier: Programming Language :: Python :: 3
Classifier: License :: OSI Approved :: BSD License
Classifier: Operating System :: OS Independent
License-File: LICENSE.txt
License-File: NOTICE.txt
Requires-Dist: rpyc (==4.0.2)
Requires-Dist: sql30 (>=0.2.2)
Requires-Dist: paramiko (>=1.17.0)
